powerchat/__init__.py
powerchat/file_utils.py
powerchat/main.py
powerchat/openai_utils.py
powerchat-0.1.0.dist-info/WHEEL
powerchat-0.1.0.dist-info/entry_points.txt
powerchat-0.1.0.dist-info/METADATA
powerchat-0.1.0.dist-info/RECORD
