Metadata-Version: 2.1
Name: powerchat
Version: 0.1.0
Summary: 
Author: Björn van Dijkman
Author-email: bjornvandijkman@gmail.com
Requires-Python: >=3.10,<4.0
Classifier: Programming Language :: Python :: 3
Classifier: Programming Language :: Python :: 3.10
Classifier: Programming Language :: Python :: 3.11
Requires-Dist: openai (>=0.27.2,<0.28.0)
Requires-Dist: pyperclip (>=1.8.2,<2.0.0)
